evohomeclient/__init__.py
evohomeclient/tests.py
evohomeclient2/__init__.py
evohomeclient2/controlsystem.py
evohomeclient2/gateway.py
evohomeclient2/hotwater.py
evohomeclient2/location.py
evohomeclient2/tests.py
evohomeclient2/zone.py
evohomeclient-0.3.9.dist-info/LICENSE.txt
evohomeclient-0.3.9.dist-info/METADATA
evohomeclient-0.3.9.dist-info/WHEEL
evohomeclient-0.3.9.dist-info/top_level.txt
evohomeclient-0.3.9.dist-info/RECORD
