Metadata-Version: 2.1
Name: evohomeclient
Version: 0.3.9
Summary: Python client for connecting to the Evohome webservice
Home-page: https://github.com/watchforstock/evohome-client/
Download-URL: https://github.com/watchforstock/evohome-client/tarball/0.3.9
Author: Andrew Stock
Author-email: evohome@andrew-stock.com
License: Apache 2
Keywords: evohome
Classifier: Development Status :: 3 - Alpha
License-File: LICENSE.txt
Requires-Dist: requests
